odoo/addons/l10n_ro_hr_payroll/README.rst
odoo/addons/l10n_ro_hr_payroll/__init__.py
odoo/addons/l10n_ro_hr_payroll/__manifest__.py
odoo/addons/l10n_ro_hr_payroll/data/hr.contribution.register.csv
odoo/addons/l10n_ro_hr_payroll/data/hr.wage.history.csv
odoo/addons/l10n_ro_hr_payroll/data/hr_salary_rule.xml
odoo/addons/l10n_ro_hr_payroll/data/hr_salary_rule_category.xml
odoo/addons/l10n_ro_hr_payroll/data/res.partner.csv
odoo/addons/l10n_ro_hr_payroll/models/__init__.py
odoo/addons/l10n_ro_hr_payroll/models/hr_employee.py
odoo/addons/l10n_ro_hr_payroll/models/hr_holidays.py
odoo/addons/l10n_ro_hr_payroll/models/hr_meal_vouchers.py
odoo/addons/l10n_ro_hr_payroll/models/hr_payroll.py
odoo/addons/l10n_ro_hr_payroll/models/hr_wage_history.py
odoo/addons/l10n_ro_hr_payroll/models/res_company.py
odoo/addons/l10n_ro_hr_payroll/report/hr_meal_vouchers.xml
odoo/addons/l10n_ro_hr_payroll/report/report_meal_vouchers_template.xml
odoo/addons/l10n_ro_hr_payroll/security/hr_security.xml
odoo/addons/l10n_ro_hr_payroll/security/ir.model.access.csv
odoo/addons/l10n_ro_hr_payroll/static/description/icon.png
odoo/addons/l10n_ro_hr_payroll/tests/__init__.py
odoo/addons/l10n_ro_hr_payroll/tests/common.py
odoo/addons/l10n_ro_hr_payroll/tests/test_hr_employee.py
odoo/addons/l10n_ro_hr_payroll/tests/test_hr_holidays.py
odoo/addons/l10n_ro_hr_payroll/tests/test_hr_meal_vouchers.py
odoo/addons/l10n_ro_hr_payroll/tests/test_hr_payroll.py
odoo/addons/l10n_ro_hr_payroll/tests/test_hr_payroll_payslips_by_employees.py
odoo/addons/l10n_ro_hr_payroll/tests/test_hr_wage_history.py
odoo/addons/l10n_ro_hr_payroll/tests/test_res_company.py
odoo/addons/l10n_ro_hr_payroll/views/hr_employee_view.xml
odoo/addons/l10n_ro_hr_payroll/views/hr_holidays_view.xml
odoo/addons/l10n_ro_hr_payroll/views/hr_meal_vouchers_view.xml
odoo/addons/l10n_ro_hr_payroll/views/hr_payroll_view.xml
odoo/addons/l10n_ro_hr_payroll/views/hr_wage_history_view.xml
odoo/addons/l10n_ro_hr_payroll/wizard/__init__.py
odoo11_addon_l10n_ro_hr_payroll-11.0.1.0.0.dist-info/METADATA
odoo11_addon_l10n_ro_hr_payroll-11.0.1.0.0.dist-info/WHEEL
odoo11_addon_l10n_ro_hr_payroll-11.0.1.0.0.dist-info/top_level.txt
odoo11_addon_l10n_ro_hr_payroll-11.0.1.0.0.dist-info/RECORD
